[
  {
    "name": "ครูไทยเพื่อประชาชน",
    "side": "government"
  },
  {
    "name": "ชาติไทยพัฒนา",
    "side": "government"
  },
  {
    "name": "ชาติพัฒนา",
    "side": "government"
  },
  {
    "name": "ไทรักธรรม",
    "side": "government"
  },
  {
    "name": "ประชาชนปฏิรูป",
    "side": "government"
  },
  {
    "name": "ประชาธรรมไทย",
    "side": "government"
  },
  {
    "name": "ประชาธิปไตยใหม่",
    "side": "government"
  },
  {
    "name": "ประชาธิปัตย์",
    "side": "government"
  },
  {
    "name": "ประชานิยม",
    "side": "government"
  },
  {
    "name": "ประชาภิวัฒน์",
    "side": "government"
  },
  {
    "name": "พลเมืองไทย",
    "side": "government"
  },
  {
    "name": "พลังชาติไทย",
    "side": "government"
  },
  {
    "name": "พลังท้องถิ่นไท",
    "side": "government"
  },
  {
    "name": "พลังไทยรักไทย",
    "side": "government"
  },
  {
    "name": "พลังธรรมใหม่",
    "side": "government"
  },
  {
    "name": "พลังประชารัฐ",
    "side": "government"
  },
  {
    "name": "ภูมิใจไทย",
    "side": "government"
  },
  {
    "name": "รวมพลังประชาชาติไทย",
    "side": "government"
  },
  {
    "name": "รักษ์ผืนป่าประเทศไทย",
    "side": "government"
  },
  {
    "name": "เศรษฐกิจใหม่",
    "side": "government"
  },
  {
    "name": "ก้าวไกล",
    "side": "opposition"
  },
  {
    "name": "ไทยศรีวิไลย์",
    "side": "opposition"
  },
  {
    "name": "ประชาชาติ",
    "side": "opposition"
  },
  {
    "name": "พลังปวงชนไทย",
    "side": "opposition"
  },
  {
    "name": "เพื่อชาติ",
    "side": "opposition"
  },
  {
    "name": "เพื่อไทย",
    "side": "opposition"
  },
  {
    "name": "เสรีรวมไทย",
    "side": "opposition"
  },
  {
    "name": "อนาคตใหม่",
    "side": "opposition"
  }
]
